Metadata-Version: 1.0
Name: gwapy
Version: 0.2
Summary: gwapy
Home-page: UNKNOWN
Author: bat-cha
Author-email: baptiste.chatrain@amadeus.com
License: MIT
Platform: UNKNOWN
